robpy/__init__.py
robpy/covariance/__init__.py
robpy/covariance/base.py
robpy/covariance/cellmcd.py
robpy/covariance/initial_ddcw.py
robpy/covariance/kendall.py
robpy/covariance/mcd.py
robpy/covariance/ogk.py
robpy/covariance/utils/alter_covariance.py
robpy/covariance/utils/cellmcd_utils.py
robpy/covariance/utils/cellmcd_visualization_utils.py
robpy/covariance/wrapping.py
robpy/datasets/__init__.py
robpy/datasets/base.py
robpy/datasets/data/animals.csv
robpy/datasets/data/glass.csv
robpy/datasets/data/stars.csv
robpy/datasets/data/telephone.csv
robpy/datasets/data/topgear.csv
robpy/datasets/descr/animals.rst
robpy/datasets/descr/glass.rst
robpy/datasets/descr/stars.rst
robpy/datasets/descr/telephone.rst
robpy/datasets/descr/topgear.rst
robpy/outliers/__init__.py
robpy/outliers/ddc.py
robpy/pca/__init__.py
robpy/pca/base.py
robpy/pca/robpca.py
robpy/pca/spca.py
robpy/preprocessing/__init__.py
robpy/preprocessing/data_cleaner.py
robpy/preprocessing/scaling.py
robpy/preprocessing/transfo.py
robpy/preprocessing/utils.py
robpy/regression/__init__.py
robpy/regression/base.py
robpy/regression/lts.py
robpy/regression/mm_estimator.py
robpy/regression/s_estimator.py
robpy/univariate/__init__.py
robpy/univariate/base.py
robpy/univariate/mcd.py
robpy/univariate/onestep_m.py
robpy/univariate/qn.py
robpy/univariate/tau.py
robpy/utils/distance.py
robpy/utils/general.py
robpy/utils/logging.py
robpy/utils/median.py
robpy/utils/outlyingness.py
robpy/utils/rho.py
robpy-0.1.0.dist-info/METADATA
robpy-0.1.0.dist-info/WHEEL
robpy-0.1.0.dist-info/RECORD
