Metadata-Version: 2.1
Name: robpy
Version: 0.1.0
Summary: 
Author: Thomas Servotte
Author-email: servottethomas@gmail.com
Requires-Python: >=3.10,<4.0
Classifier: Programming Language :: Python :: 3
Classifier: Programming Language :: Python :: 3.10
Classifier: Programming Language :: Python :: 3.11
Classifier: Programming Language :: Python :: 3.12
Requires-Dist: matplotlib (>=3.8.2,<4.0.0)
Requires-Dist: scikit-learn (>=1.3)
Requires-Dist: scipy (>=1.11.4,<2.0.0)
Requires-Dist: seaborn (>=0.13.2,<0.14.0)
Requires-Dist: statsmodels (>=0.14.1,<0.15.0)
Requires-Dist: tqdm (>=4.66.1,<5.0.0)
